Workbook

Sheet Ventas
A1: Fecha | B1: ID_Producto | C1: Nombre | D1: Categoría | E1: Cantidad | F1: Precio_Venta | G1: Vendedor | H1: Subtotal | I1: Stock_Actual | J1: Stock_Mínimo
A2: 45717 | B2: P001 | C2: Coca Cola 2.25L | D2: Bebidas | E2: 12 | F2: 850 | G2: Maxi | H2: =Registro_Ventas[Cantidad] * Registro_Ventas[Precio_Venta] -> 10200 | I2: =VLOOKUP(B2, Productos!A:E, 4, FALSE) -> 4 | J2: =VLOOKUP(B2, Productos!A:E, 5, FALSE) -> 20
A3: 45717 | B3: P002 | C3: Agua Mineral 500ml | D3: Bebidas | E3: 8 | F3: 320 | G3: Maxi | H3: =Registro_Ventas[Cantidad] * Registro_Ventas[Precio_Venta] -> 2560 | I3: =VLOOKUP(B3, Productos!A:E, 4, FALSE) -> 35 | J3: =VLOOKUP(B3, Productos!A:E, 5, FALSE) -> 15
A4: 45717 | B4: P003 | C4: Arroz Largo Fino 1kg | D4: Almacén | E4: 5 | F4: 1200 | G4: Maxi | H4: =Registro_Ventas[Cantidad] * Registro_Ventas[Precio_Venta] -> 6000 | I4: =VLOOKUP(B4, Productos!A:E, 4, FALSE) -> 8 | J4: =VLOOKUP(B4, Productos!A:E, 5, FALSE) -> 10
A5: 45718 | B5: P001 | C5: Coca Cola 2.25L | D5: Bebidas | E5: 6 | F5: 850 | G5: Maxi | H5: =Registro_Ventas[Cantidad] * Registro_Ventas[Precio_Venta] -> 5100 | I5: =VLOOKUP(B5, Productos!A:E, 4, FALSE) -> 4 | J5: =VLOOKUP(B5, Productos!A:E, 5, FALSE) -> 20
A6: 45718 | B6: P004 | C6: Aceite Girasol 900ml | D6: Almacén | E6: 4 | F6: 1800 | G6: Maxi | H6: =Registro_Ventas[Cantidad] * Registro_Ventas[Precio_Venta] -> 7200 | I6: =VLOOKUP(B6, Productos!A:E, 4, FALSE) -> 6 | J6: =VLOOKUP(B6, Productos!A:E, 5, FALSE) -> 8
A7: 45718 | B7: P005 | C7: Galletitas Oreo 117g | D7: Snacks | E7: 10 | F7: 650 | G7: Maxi | H7: =Registro_Ventas[Cantidad] * Registro_Ventas[Precio_Venta] -> 6500 | I7: =VLOOKUP(B7, Productos!A:E, 4, FALSE) -> 3 | J7: =VLOOKUP(B7, Productos!A:E, 5, FALSE) -> 12
A8: 45719 | B8: P003 | C8: Arroz Largo Fino 1kg | D8: Almacén | E8: 3 | F8: 1200 | G8: Maxi | H8: =Registro_Ventas[Cantidad] * Registro_Ventas[Precio_Venta] -> 3600 | I8: =VLOOKUP(B8, Productos!A:E, 4, FALSE) -> 8 | J8: =VLOOKUP(B8, Productos!A:E, 5, FALSE) -> 10
A9: 45719 | B9: P006 | C9: Yogur Entero 190g | D9: Lácteos | E9: 9 | F9: 480 | G9: Maxi | H9: =Registro_Ventas[Cantidad] * Registro_Ventas[Precio_Venta] -> 4320 | I9: =VLOOKUP(B9, Productos!A:E, 4, FALSE) -> 14 | J9: =VLOOKUP(B9, Productos!A:E, 5, FALSE) -> 10
A10: 45719 | B10: P007 | C10: Leche Entera 1L | D10: Lácteos | E10: 14 | F10: 720 | G10: Maxi | H10: =Registro_Ventas[Cantidad] * Registro_Ventas[Precio_Venta] -> 10080 | I10: =VLOOKUP(B10, Productos!A:E, 4, FALSE) -> 7 | J10: =VLOOKUP(B10, Productos!A:E, 5, FALSE) -> 15
A11: 45729 | B11: P006 | C11: Yogur Entero 190g | D11: Lácteos | E11: 7 | F11: 480 | G11: Maxi | H11: =Registro_Ventas[Cantidad] * Registro_Ventas[Precio_Venta] -> 3360 | I11: =VLOOKUP(B11, Productos!A:E, 4, FALSE) -> 14 | J11: =VLOOKUP(B11, Productos!A:E, 5, FALSE) -> 10
A12: 45729 | B12: P013 | C12: Mermelada Frutilla 390g | D12: Almacén | E12: 3 | F12: 1050 | G12: Maxi | H12: =Registro_Ventas[Cantidad] * Registro_Ventas[Precio_Venta] -> 3150 | I12: =VLOOKUP(B12, Productos!A:E, 4, FALSE) -> 12 | J12: =VLOOKUP(B12, Productos!A:E, 5, FALSE) -> 8
A13: 45730 | B13: P003 | C13: Arroz Largo Fino 1kg | D13: Almacén | E13: 4 | F13: 1200 | G13: Maxi | H13: =Registro_Ventas[Cantidad] * Registro_Ventas[Precio_Venta] -> 4800 | I13: =VLOOKUP(B13, Productos!A:E, 4, FALSE) -> 8 | J13: =VLOOKUP(B13, Productos!A:E, 5, FALSE) -> 10
... A41: 45767 | B41: P015 | C41: Manteca 200g | D41: Lácteos | E41: 5 | F41: 1400 | G41: Maxi | H41: =Registro_Ventas[Cantidad] * Registro_Ventas[Precio_Venta] -> 7000 | I41: =VLOOKUP(B41, Productos!A:E, 4, FALSE) -> 19 | J41: =VLOOKUP(B41, Productos!A:E, 5, FALSE) -> 10

Sheet Productos
A1: ID_Producto | B1: Nombre | C1: Costo_Unitario | D1: Stock_Actual | E1: Stock_Mínimo | F1: Total_Vendido | G1: Venta_Promedio_Diaria | H1: Días_Stock_Restante | I1: Estado | J1: Unidades_Para_Recuperar_Minimo | K1: Costo_Reposición | L1: Categoría | M1: Ingreso_Total | N1: Ingreso_Promedio_Diario | O1: Exposición_Semanal_Ventas | Q1: Producto | R1: Días_Cobertura | T1: Producto | U1: Exposición_Semanal_Ventas
A2: P001 | B2: Coca Cola 2.25L | C2: 580 | D2: 4 | E2: 20 | F2: =SUMIF(Ventas!B:B,A2, Ventas!E:E) -> 34 | G2: =F2/(MAX(Ventas!A:A)-MIN(Ventas!A:A)+1) -> 0.66666667 | H2: =IF(G2=0, "N/A", D2/G2) -> 6 | I2: =IF(G2=0,"Sin rotación", IF(H2<=7,"URGENTE", IF(H2<=14,"Atención","OK"))) -> URGENTE | J2: =MAX(0,E2-D2) -> 16 | K2: =J2*C2 -> 9280 | L2: =VLOOKUP(A2, Ventas!B:D, 3, 0) -> Bebidas | M2: =SUMIF(Ventas!B:B, A2, Ventas!H:H) -> 28900 | N2: =M2/(MAX(Ventas!A:A)-MIN(Ventas!A:A)+1) -> 566.66667 | O2: =N2*7 -> 3966.6667 | Q2: Galletitas Oreo 117g | R2: 4.9354839 | T2: Leche Entera 1L | U2: 4644.7059
A3: P002 | B3: Agua Mineral 500ml | C3: 190 | D3: 35 | E3: 15 | F3: =SUMIF(Ventas!B:B,A3, Ventas!E:E) -> 47 | G3: =F3/(MAX(Ventas!A:A)-MIN(Ventas!A:A)+1) -> 0.92156863 | H3: =IF(G3=0, "N/A", D3/G3) -> 37.978723 | I3: =IF(G3=0,"Sin rotación", IF(H3<=7,"URGENTE", IF(H3<=14,"Atención","OK"))) -> OK | J3: =MAX(0,E3-D3) -> 0 | K3: =J3*C3 -> 0 | L3: =VLOOKUP(A3, Ventas!B:D, 3, 0) -> Bebidas | M3: =SUMIF(Ventas!B:B, A3, Ventas!H:H) -> 15040 | N3: =M3/(MAX(Ventas!A:A)-MIN(Ventas!A:A)+1) -> 294.90196 | O3: =N3*7 -> 2064.3137 | Q3: Coca Cola 2.25L | R3: 6 | T3: Coca Cola 2.25L | U3: 3966.6667
A4: P003 | B4: Arroz Largo Fino 1kg | C4: 780 | D4: 8 | E4: 10 | F4: =SUMIF(Ventas!B:B,A4, Ventas!E:E) -> 18 | G4: =F4/(MAX(Ventas!A:A)-MIN(Ventas!A:A)+1) -> 0.35294118 | H4: =IF(G4=0, "N/A", D4/G4) -> 22.666667 | I4: =IF(G4=0,"Sin rotación", IF(H4<=7,"URGENTE", IF(H4<=14,"Atención","OK"))) -> OK | J4: =MAX(0,E4-D4) -> 2 | K4: =J4*C4 -> 1560 | L4: =VLOOKUP(A4, Ventas!B:D, 3, 0) -> Almacén | M4: =SUMIF(Ventas!B:B, A4, Ventas!H:H) -> 21600 | N4: =M4/(MAX(Ventas!A:A)-MIN(Ventas!A:A)+1) -> 423.52941 | O4: =N4*7 -> 2964.7059 | Q4: Leche Entera 1L | R4: 7.5957447 | T4: Papel Higiénico x4 | U4: 2779.4118
A5: P004 | B5: Aceite Girasol 900ml | C5: 1200 | D5: 6 | E5: 8 | F5: =SUMIF(Ventas!B:B,A5, Ventas!E:E) -> 9 | G5: =F5/(MAX(Ventas!A:A)-MIN(Ventas!A:A)+1) -> 0.17647059 | H5: =IF(G5=0, "N/A", D5/G5) -> 34 | I5: =IF(G5=0,"Sin rotación", IF(H5<=7,"URGENTE", IF(H5<=14,"Atención","OK"))) -> OK | J5: =MAX(0,E5-D5) -> 2 | K5: =J5*C5 -> 2400 | L5: =VLOOKUP(A5, Ventas!B:D, 3, 0) -> Almacén | M5: =SUMIF(Ventas!B:B, A5, Ventas!H:H) -> 16200 | N5: =M5/(MAX(Ventas!A:A)-MIN(Ventas!A:A)+1) -> 317.64706 | O5: =N5*7 -> 2223.5294 | Q5: Papel Higiénico x4 | R5: 10.2 | T5: Galletitas Oreo 117g | U5: 2765.6863
A6: P005 | B6: Galletitas Oreo 117g | C6: 400 | D6: 3 | E6: 12 | F6: =SUMIF(Ventas!B:B,A6, Ventas!E:E) -> 31 | G6: =F6/(MAX(Ventas!A:A)-MIN(Ventas!A:A)+1) -> 0.60784314 | H6: =IF(G6=0, "N/A", D6/G6) -> 4.9354839 | I6: =IF(G6=0,"Sin rotación", IF(H6<=7,"URGENTE", IF(H6<=14,"Atención","OK"))) -> URGENTE | J6: =MAX(0,E6-D6) -> 9 | K6: =J6*C6 -> 3600 | L6: =VLOOKUP(A6, Ventas!B:D, 3, 0) -> Snacks | M6: =SUMIF(Ventas!B:B, A6, Ventas!H:H) -> 20150 | N6: =M6/(MAX(Ventas!A:A)-MIN(Ventas!A:A)+1) -> 395.09804 | O6: =N6*7 -> 2765.6863 | Q6: Lavandina 1L | R6: 11.333333 | T6: Lavandina 1L | U6: 1358.8235
A7: P006 | B7: Yogur Entero 190g | C7: 290 | D7: 14 | E7: 10 | F7: =SUMIF(Ventas!B:B,A7, Ventas!E:E) -> 21 | G7: =F7/(MAX(Ventas!A:A)-MIN(Ventas!A:A)+1) -> 0.41176471 | H7: =IF(G7=0, "N/A", D7/G7) -> 34 | I7: =IF(G7=0,"Sin rotación", IF(H7<=7,"URGENTE", IF(H7<=14,"Atención","OK"))) -> OK | J7: =MAX(0,E7-D7) -> 0 | K7: =J7*C7 -> 0 | L7: =VLOOKUP(A7, Ventas!B:D, 3, 0) -> Lácteos | M7: =SUMIF(Ventas!B:B, A7, Ventas!H:H) -> 10080 | N7: =M7/(MAX(Ventas!A:A)-MIN(Ventas!A:A)+1) -> 197.64706 | O7: =N7*7 -> 1383.5294 | Q7: Arroz Largo Fino 1kg | R7: 22.666667
A8: P007 | B8: Leche Entera 1L | C8: 480 | D8: 7 | E8: 15 | F8: =SUMIF(Ventas!B:B,A8, Ventas!E:E) -> 47 | G8: =F8/(MAX(Ventas!A:A)-MIN(Ventas!A:A)+1) -> 0.92156863 | H8: =IF(G8=0, "N/A", D8/G8) -> 7.5957447 | I8: =IF(G8=0,"Sin rotación", IF(H8<=7,"URGENTE", IF(H8<=14,"Atención","OK"))) -> Atención | J8: =MAX(0,E8-D8) -> 8 | K8: =J8*C8 -> 3840 | L8: =VLOOKUP(A8, Ventas!B:D, 3, 0) -> Lácteos | M8: =SUMIF(Ventas!B:B, A8, Ventas!H:H) -> 33840 | N8: =M8/(MAX(Ventas!A:A)-MIN(Ventas!A:A)+1) -> 663.52941 | O8: =N8*7 -> 4644.7059 | Q8: Atún al Natural 170g | R8: 23.181818
A9: P008 | B9: Jabón Líquido 750ml | C9: 700 | D9: 11 | E9: 8 | F9: =SUMIF(Ventas!B:B,A9, Ventas!E:E) -> 11 | G9: =F9/(MAX(Ventas!A:A)-MIN(Ventas!A:A)+1) -> 0.21568627 | H9: =IF(G9=0, "N/A", D9/G9) -> 51 | I9: =IF(G9=0,"Sin rotación", IF(H9<=7,"URGENTE", IF(H9<=14,"Atención","OK"))) -> OK | J9: =MAX(0,E9-D9) -> 0 | K9: =J9*C9 -> 0 | L9: =VLOOKUP(A9, Ventas!B:D, 3, 0) -> Limpieza | M9: =SUMIF(Ventas!B:B, A9, Ventas!H:H) -> 12100 | N9: =M9/(MAX(Ventas!A:A)-MIN(Ventas!A:A)+1) -> 237.2549 | O9: =N9*7 -> 1660.7843 | Q9: Aceite Girasol 900ml | R9: 34
A10: P009 | B10: Lavandina 1L | C10: 320 | D10: 4 | E10: 10 | F10: =SUMIF(Ventas!B:B,A10, Ventas!E:E) -> 18 | G10: =F10/(MAX(Ventas!A:A)-MIN(Ventas!A:A)+1) -> 0.35294118 | H10: =IF(G10=0, "N/A", D10/G10) -> 11.333333 | I10: =IF(G10=0,"Sin rotación", IF(H10<=7,"URGENTE", IF(H10<=14,"Atención","OK"))) -> Atención | J10: =MAX(0,E10-D10) -> 6 | K10: =J10*C10 -> 1920 | L10: =VLOOKUP(A10, Ventas!B:D, 3, 0) -> Limpieza | M10: =SUMIF(Ventas!B:B, A10, Ventas!H:H) -> 9900 | N10: =M10/(MAX(Ventas!A:A)-MIN(Ventas!A:A)+1) -> 194.11765 | O10: =N10*7 -> 1358.8235 | Q10: Yogur Entero 190g | R10: 34
A11: P010 | B11: Fideos Spaghetti 500g | C11: 560 | D11: 16 | E11: 10 | F11: =SUMIF(Ventas!B:B,A11, Ventas!E:E) -> 16 | G11: =F11/(MAX(Ventas!A:A)-MIN(Ventas!A:A)+1) -> 0.31372549 | H11: =IF(G11=0, "N/A", D11/G11) -> 51 | I11: =IF(G11=0,"Sin rotación", IF(H11<=7,"URGENTE", IF(H11<=14,"Atención","OK"))) -> OK | J11: =MAX(0,E11-D11) -> 0 | K11: =J11*C11 -> 0 | L11: =VLOOKUP(A11, Ventas!B:D, 3, 0) -> Almacén | M11: =SUMIF(Ventas!B:B, A11, Ventas!H:H) -> 14240 | N11: =M11/(MAX(Ventas!A:A)-MIN(Ventas!A:A)+1) -> 279.21569 | O11: =N11*7 -> 1954.5098 | Q11: Agua Mineral 500ml | R11: 37.978723
A12: P011 | B12: Detergente Magistral 500ml | C12: 620 | D12: 9 | E12: 8 | F12: =SUMIF(Ventas!B:B,A12, Ventas!E:E) -> 10 | G12: =F12/(MAX(Ventas!A:A)-MIN(Ventas!A:A)+1) -> 0.19607843 | H12: =IF(G12=0, "N/A", D12/G12) -> 45.9 | I12: =IF(G12=0,"Sin rotación", IF(H12<=7,"URGENTE", IF(H12<=14,"Atención","OK"))) -> OK | J12: =MAX(0,E12-D12) -> 0 | K12: =J12*C12 -> 0 | L12: =VLOOKUP(A12, Ventas!B:D, 3, 0) -> Limpieza | M12: =SUMIF(Ventas!B:B, A12, Ventas!H:H) -> 9800 | N12: =M12/(MAX(Ventas!A:A)-MIN(Ventas!A:A)+1) -> 192.15686 | O12: =N12*7 -> 1345.098 | Q12: Detergente Magistral 500ml | R12: 45.9
A13: P012 | B13: Papel Higiénico x4 | C13: 850 | D13: 3 | E13: 6 | F13: =SUMIF(Ventas!B:B,A13, Ventas!E:E) -> 15 | G13: =F13/(MAX(Ventas!A:A)-MIN(Ventas!A:A)+1) -> 0.29411765 | H13: =IF(G13=0, "N/A", D13/G13) -> 10.2 | I13: =IF(G13=0,"Sin rotación", IF(H13<=7,"URGENTE", IF(H13<=14,"Atención","OK"))) -> Atención | J13: =MAX(0,E13-D13) -> 3 | K13: =J13*C13 -> 2550 | L13: =VLOOKUP(A13, Ventas!B:D, 3, 0) -> Limpieza | M13: =SUMIF(Ventas!B:B, A13, Ventas!H:H) -> 20250 | N13: =M13/(MAX(Ventas!A:A)-MIN(Ventas!A:A)+1) -> 397.05882 | O13: =N13*7 -> 2779.4118 | Q13: Jabón Líquido 750ml | R13: 51
A14: P013 | B14: Mermelada Frutilla 390g | C14: 680 | D14: 12 | E14: 8 | F14: =SUMIF(Ventas!B:B,A14, Ventas!E:E) -> 7 | G14: =F14/(MAX(Ventas!A:A)-MIN(Ventas!A:A)+1) -> 0.1372549 | H14: =IF(G14=0, "N/A", D14/G14) -> 87.428571 | I14: =IF(G14=0,"Sin rotación", IF(H14<=7,"URGENTE", IF(H14<=14,"Atención","OK"))) -> OK | J14: =MAX(0,E14-D14) -> 0 | K14: =J14*C14 -> 0 | L14: =VLOOKUP(A14, Ventas!B:D, 3, 0) -> Almacén | M14: =SUMIF(Ventas!B:B, A14, Ventas!H:H) -> 7350 | N14: =M14/(MAX(Ventas!A:A)-MIN(Ventas!A:A)+1) -> 144.11765 | O14: =N14*7 -> 1008.8235 | Q14: Fideos Spaghetti 500g | R14: 51
A15: P014 | B15: Atún al Natural 170g | C15: 490 | D15: 5 | E15: 8 | F15: =SUMIF(Ventas!B:B,A15, Ventas!E:E) -> 11 | G15: =F15/(MAX(Ventas!A:A)-MIN(Ventas!A:A)+1) -> 0.21568627 | H15: =IF(G15=0, "N/A", D15/G15) -> 23.181818 | I15: =IF(G15=0,"Sin rotación", IF(H15<=7,"URGENTE", IF(H15<=14,"Atención","OK"))) -> OK | J15: =MAX(0,E15-D15) -> 3 | K15: =J15*C15 -> 1470 | L15: =VLOOKUP(A15, Ventas!B:D, 3, 0) -> Almacén | M15: =SUMIF(Ventas!B:B, A15, Ventas!H:H) -> 8580 | N15: =M15/(MAX(Ventas!A:A)-MIN(Ventas!A:A)+1) -> 168.23529 | O15: =N15*7 -> 1177.6471 | Q15: Mermelada Frutilla 390g | R15: 87.428571
A16: P015 | B16: Manteca 200g | C16: 950 | D16: 19 | E16: 10 | F16: =SUMIF(Ventas!B:B,A16, Ventas!E:E) -> 5 | G16: =F16/(MAX(Ventas!A:A)-MIN(Ventas!A:A)+1) -> 0.098039216 | H16: =IF(G16=0, "N/A", D16/G16) -> 193.8 | I16: =IF(G16=0,"Sin rotación", IF(H16<=7,"URGENTE", IF(H16<=14,"Atención","OK"))) -> OK | J16: =MAX(0,E16-D16) -> 0 | K16: =J16*C16 -> 0 | L16: =VLOOKUP(A16, Ventas!B:D, 3, 0) -> Lácteos | M16: =SUMIF(Ventas!B:B, A16, Ventas!H:H) -> 7000 | N16: =M16/(MAX(Ventas!A:A)-MIN(Ventas!A:A)+1) -> 137.2549 | O16: =N16*7 -> 960.78431 | Q16: Manteca 200g | R16: 193.8
A18: Costo total de reposición (todos los productos bajo minimo): | B18: =SUM(K2:K16) -> 26620
A19: Costo de reposición — solo productos URGENTE: | B19: =SUMIF(I2:I16, "URGENTE", K2:K16) -> 12880
A21: Categoría | B21: Cantidad_Productos | C21: Productos_En_Riesgo | D21: Costo_Para_Recuperar_Mínimo
A22: Bebidas | B22: =COUNTIF($L$2:$L$16, A22) -> 2 | C22: =COUNTIFS($L$2:$L$16 ,A22 ,$I$2:$I$16, "<>OK") -> 1 | D22: =SUMIF($L$2:$L$16,A22,$K$2:$K$16) -> 9280
A23: Almacén | B23: =COUNTIF($L$2:$L$16, A23) -> 5 | C23: =COUNTIFS($L$2:$L$16 ,A23 ,$I$2:$I$16, "<>OK") -> 0 | D23: =SUMIF($L$2:$L$16,A23,$K$2:$K$16) -> 5430
A24: Snacks | B24: =COUNTIF($L$2:$L$16, A24) -> 1 | C24: =COUNTIFS($L$2:$L$16 ,A24 ,$I$2:$I$16, "<>OK") -> 1 | D24: =SUMIF($L$2:$L$16,A24,$K$2:$K$16) -> 3600
A25: Lácteos | B25: =COUNTIF($L$2:$L$16, A25) -> 3 | C25: =COUNTIFS($L$2:$L$16 ,A25 ,$I$2:$I$16, "<>OK") -> 1 | D25: =SUMIF($L$2:$L$16,A25,$K$2:$K$16) -> 3840
A26: Limpieza | B26: =COUNTIF($L$2:$L$16, A26) -> 4 | C26: =COUNTIFS($L$2:$L$16 ,A26 ,$I$2:$I$16, "<>OK") -> 2 | D26: =SUMIF($L$2:$L$16,A26,$K$2:$K$16) -> 4470

Sheet Dashboard
B1: Dashboard - Análisis de Quiebres de Stock
B3: Productos Analizados | D3: Productos en Riesgo | F3: Urgentes | H3: Costo Repos. Urgente
B4: =COUNTA(Productos!A2:A16) -> 15 | D4: =COUNTIF(Productos!I2:I16,"<>OK") -> 5 | F4: =COUNTIF(Productos!I2:I16,"URGENTE") -> 2 | H4: =Productos!B19 -> 12880
